retrotool/script.py
retrotool/snes.py
retrotool-0.1.1.dist-info/LICENSE
retrotool-0.1.1.dist-info/METADATA
retrotool-0.1.1.dist-info/WHEEL
retrotool-0.1.1.dist-info/top_level.txt
retrotool-0.1.1.dist-info/RECORD
