Metadata-Version: 2.2
Name: retrotool
Version: 0.1.1
Summary: Address Conversion Tool for the Super Famicom
Author-email: Daniel Burgess <daniel@herotechsys.com>
License: This is free and unencumbered software released into the public domain.
Project-URL: Homepage, https://github.com/danielburgess/SFCRetroTools
Requires-Python: >=3.8
License-File: LICENSE
Requires-Dist: chardet>=5.2.0
